plot2vid/__init__.py
plot2vid-1.0.3.dist-info/METADATA
plot2vid-1.0.3.dist-info/WHEEL
plot2vid-1.0.3.dist-info/licenses/LICENSE
plot2vid-1.0.3.dist-info/RECORD
