Metadata-Version: 2.1
Name: plot2vid
Version: 1.0.3
Summary: The easiest way to create animations using plots.
Project-URL: Homepage, https://github.com/fszewczyk/plot2vid
Author-email: Franciszek Szewczyk <szewczyk.franciszek02@gmail.com>
License: /*
License-File: LICENSE
Keywords: animation,plot,video
Classifier: Programming Language :: Python
Classifier: Programming Language :: Python :: 3
Requires-Python: >=3.9
Requires-Dist: matplotlib>=3.6.0
Requires-Dist: numpy>=1.24.3
Requires-Dist: opencv-python>=4.6.0.66
